retunnel/__init__.py
retunnel/client/__init__.py
retunnel/client/api_client.py
retunnel/client/cli.py
retunnel/client/client.py
retunnel/client/config_manager.py
retunnel/client/high_performance_model.py
retunnel/core/__init__.py
retunnel/core/api.py
retunnel/core/config.py
retunnel/core/connection.py
retunnel/core/exceptions.py
retunnel/core/protocol.py
retunnel/utils/__init__.py
retunnel/utils/id.py
retunnel-2.5.3.dist-info/licenses/LICENSE
retunnel-2.5.3.dist-info/METADATA
retunnel-2.5.3.dist-info/WHEEL
retunnel-2.5.3.dist-info/entry_points.txt
retunnel-2.5.3.dist-info/top_level.txt
retunnel-2.5.3.dist-info/RECORD
